connectkit_database-2.2.1.dist-info/METADATA
connectkit_database-2.2.1.dist-info/WHEEL
connectkit_database-2.2.1.dist-info/entry_points.txt
connectkit_database-2.2.1.dist-info/licenses/LICENSE
database/__init__.py
database/asyncio/__init__.py
database/asyncio/init_base.py
database/asyncio/session.py
database/capability_check.py
database/errors.py
database/init_base.py
database/session.py
database/settings.py
database/util.py
connectkit_database-2.2.1.dist-info/RECORD
