Metadata-Version: 2.1
Name: ConnectKit-Database
Version: 2.2.1
Summary: Wrapper for connection to database
Keywords: connectkit,database,postgres,postgresql,mysql,sqlite3,sqlite,mariadb,async,asyncio,sqlalchemy
Author-Email: RealMetamorph <andr.timchuk@yandex.ru>
License: The MIT License (MIT)
Classifier: Development Status :: 5 - Production/Stable
Classifier: Programming Language :: Python :: 3
Classifier: Topic :: Database :: Front-Ends
Classifier: Intended Audience :: Developers
Classifier: License :: OSI Approved :: MIT License
Project-URL: Homepage, https://github.com/mtuciru/ConnectKit-Database/blob/2.2.1/README.md
Project-URL: Repository, https://github.com/mtuciru/ConnectKit-Database.git
Requires-Python: >=3.10
Requires-Dist: sqlalchemy>=2.0.39
Requires-Dist: pydantic>=2.10.6
Requires-Dist: pydantic-settings>=2.8.1
Provides-Extra: postgresql
Requires-Dist: psycopg[binary]>=3.2.6; extra == "postgresql"
Provides-Extra: asyncpg
Requires-Dist: psycopg[binary]>=3.2.6; extra == "asyncpg"
Requires-Dist: sqlalchemy[asyncio]>=2.0.39; extra == "asyncpg"
Provides-Extra: mysql
Requires-Dist: mysqlclient>=2.2.7; extra == "mysql"
Provides-Extra: aiomysql
Requires-Dist: aiomysql>=0.2.0; extra == "aiomysql"
Requires-Dist: sqlalchemy[asyncio]>=2.0.39; extra == "aiomysql"
Provides-Extra: aiosqlite
Requires-Dist: aiosqlite>=0.21.0; extra == "aiosqlite"
Requires-Dist: sqlalchemy[asyncio]>=2.0.39; extra == "aiosqlite"
Provides-Extra: all
Requires-Dist: ConnectKit-Database[mysql,postgresql]; extra == "all"
Provides-Extra: asyncall
Requires-Dist: ConnectKit-Database[aiomysql,aiosqlite,asyncpg]; extra == "asyncall"
Provides-Extra: orjson
Requires-Dist: orjson>=3.10.15; extra == "orjson"
